qudas/__init__.py
qudas/annealing/__init__.py
qudas/annealing/block.py
qudas/annealing/executor.py
qudas/annealing/input.py
qudas/annealing/ir.py
qudas/annealing/output.py
qudas/core/__init__.py
qudas/core/base.py
qudas/core/executor_base.py
qudas/core/input_base.py
qudas/core/output_base.py
qudas/gate/__init__.py
qudas/gate/block.py
qudas/gate/executor.py
qudas/gate/gate_ir.py
qudas/gate/input.py
qudas/gate/ir.py
qudas/gate/output.py
qudas/pipeline/__init__.py
qudas/pipeline/pipeline.py
qudas/pipeline/steps/__init__.py
qudas/pipeline/steps/base.py
qudas/pipeline/steps/iterator_mixin.py
qudas/pipeline/steps/optimizer_mixin.py
qudas/qudata/__init__.py
qudas/qudata/qudata.py
qudas/qudata/qudata_base.py
qudas/qudata/qudata_input.py
qudas/qudata/qudata_output.py
qudas-0.2.0.dist-info/LICENSE
qudas-0.2.0.dist-info/METADATA
qudas-0.2.0.dist-info/WHEEL
qudas-0.2.0.dist-info/top_level.txt
qudas-0.2.0.dist-info/RECORD
