Metadata-Version: 2.1
Name: qudas
Version: 0.2.0
Summary: Quantum data transform package
Author-email: Keiichiro Higa <higa.devel@gmail.com>
Project-URL: homepage, https://github.com/devel-system/qudas
Classifier: Programming Language :: Python :: 3
Classifier: License :: OSI Approved :: Apache Software License
Classifier: Operating System :: OS Independent
Requires-Python: >=3.8
License-File: LICENSE
Requires-Dist: alabaster==0.7.13
Requires-Dist: amplify==1.0.1
Requires-Dist: Babel==2.14.0
Requires-Dist: backports.tarfile==1.2.0
Requires-Dist: beautifulsoup4==4.12.3
Requires-Dist: certifi==2024.2.2
Requires-Dist: charset-normalizer==3.3.2
Requires-Dist: click==8.1.7
Requires-Dist: contourpy==1.1.1
Requires-Dist: cycler==0.12.1
Requires-Dist: Deprecated==1.2.14
Requires-Dist: dill==0.3.8
Requires-Dist: dimod==0.12.14
Requires-Dist: docutils==0.20.1
Requires-Dist: dwave-neal==0.6.0
Requires-Dist: dwave-samplers==1.2.0
Requires-Dist: filelock==3.13.1
Requires-Dist: fonttools==4.49.0
Requires-Dist: fsspec==2024.2.0
Requires-Dist: idna==3.6
Requires-Dist: imagesize==1.4.1
Requires-Dist: importlib-metadata==7.0.1
Requires-Dist: importlib-resources==6.3.0
Requires-Dist: jaraco.classes==3.4.0
Requires-Dist: jaraco.context==6.0.1
Requires-Dist: jaraco.functools==4.1.0
Requires-Dist: Jinja2==3.1.3
Requires-Dist: joblib==1.3.2
Requires-Dist: keyring==25.4.1
Requires-Dist: kiwisolver==1.4.5
Requires-Dist: markdown-it-py==3.0.0
Requires-Dist: MarkupSafe==2.1.5
Requires-Dist: matplotlib==3.7.5
Requires-Dist: mdurl==0.1.2
Requires-Dist: more-itertools==10.5.0
Requires-Dist: mpmath==1.3.0
Requires-Dist: mypy-extensions==1.0.0
Requires-Dist: networkx==3.1
Requires-Dist: nh3==0.2.18
Requires-Dist: numpy==1.24.4
Requires-Dist: packaging==23.2
Requires-Dist: pandas==2.0.3
Requires-Dist: pathspec==0.12.1
Requires-Dist: pbr==6.0.0
Requires-Dist: pillow==10.2.0
Requires-Dist: pkginfo==1.10.0
Requires-Dist: platformdirs==4.3.6
Requires-Dist: psutil==5.9.8
Requires-Dist: PuLP==2.8.0
Requires-Dist: Pygments==2.17.2
Requires-Dist: pylatexenc==2.10
Requires-Dist: pyparsing==3.1.2
Requires-Dist: pyproject-hooks==1.2.0
Requires-Dist: pyqubo==1.4.0
Requires-Dist: python-dateutil==2.8.2
Requires-Dist: pytz==2024.1
Requires-Dist: qiskit==1.0.2
Requires-Dist: qiskit-aer==0.14.1
Requires-Dist: requests==2.31.0
Requires-Dist: requests-toolbelt==1.0.0
Requires-Dist: rfc3986==2.0.0
Requires-Dist: rich==13.9.3
Requires-Dist: rustworkx==0.14.2
Requires-Dist: scikit-learn==1.3.2
Requires-Dist: scipy==1.10.1
Requires-Dist: six==1.16.0
Requires-Dist: snowballstemmer==2.2.0
Requires-Dist: soupsieve==2.5
Requires-Dist: symengine==0.11.0
Requires-Dist: sympy==1.12
Requires-Dist: threadpoolctl==3.3.0
Requires-Dist: tomli==2.0.2
Requires-Dist: tqdm==4.66.2
Requires-Dist: typing-extensions==4.9.0
Requires-Dist: tzdata==2023.4
Requires-Dist: urllib3==2.2.0
Requires-Dist: wrapt==1.16.0
Requires-Dist: zipp==3.17.0
Provides-Extra: dev
Requires-Dist: black==24.8.0; extra == "dev"
Requires-Dist: build==1.2.2.post1; extra == "dev"
Requires-Dist: flake8; extra == "dev"
Requires-Dist: pytest; extra == "dev"
Requires-Dist: python-dotenv==1.0.1; extra == "dev"
Requires-Dist: sphinx==7.1.2; extra == "dev"
Requires-Dist: sphinx-basic-ng==1.0.0b2; extra == "dev"
Requires-Dist: furo==2024.1.29; extra == "dev"
Requires-Dist: twine==5.1.1; extra == "dev"
Requires-Dist: readme-renderer==43.0; extra == "dev"
Provides-Extra: test
Requires-Dist: torch==2.2.0; extra == "test"
